README.md
setup.py
src/mistake/__init__.py
src/mistake/domain.py
src/mistake/frontend.py
src/mistake/mistake_grammar.md
src/mistake/planning.py
src/mistake/runtime.py
src/mistake/utility.py
src/mistake/version.py
src/mistake.egg-info/PKG-INFO
src/mistake.egg-info/SOURCES.txt
src/mistake.egg-info/dependency_links.txt
src/mistake.egg-info/requires.txt
src/mistake.egg-info/top_level.txt