Metadata-Version: 2.1
Name: mistake
Version: 0.0.3
Summary: A tensor-oriented programming language with semantic validation
Home-page: https://github.com/kjosib/mistake
Author: Ian Kjos
Author-email: kjosib@gmail.com
License: MIT
Platform: UNKNOWN
Classifier: Programming Language :: Python :: 3
Classifier: License :: OSI Approved :: MIT License
Classifier: Operating System :: OS Independent
Classifier: Development Status :: 1 - Planning
Classifier: Intended Audience :: Developers
Classifier: Topic :: Software Development :: Interpreters
Classifier: Topic :: Software Development :: Libraries
Requires-Python: >=3.7
